pythonsay/draws.py
pythonsay/pythonsay.py
pythonsay-0.0.2.dist-info/METADATA
pythonsay-0.0.2.dist-info/WHEEL
pythonsay-0.0.2.dist-info/top_level.txt
pythonsay-0.0.2.dist-info/RECORD
