Metadata-Version: 2.1
Name: pythonsay
Version: 0.0.2
Summary: A small example package for the pythonsay project. The main purpose is to show how to create a package with automated tests.
Author-email: Matheus Cafalchio <mcafalchio@gmail.com>
Project-URL: Homepage, https://github.com/cafalchio/pythonsay
Project-URL: Bug Tracker, https://github.com/cafalchio/pythonsay/issues
Classifier: Programming Language :: Python :: 3
Classifier: License :: OSI Approved :: MIT License
Classifier: Operating System :: OS Independent
Requires-Python: >=3.7
